README.md
setup.py
AISimuToolKit/__init__.py
AISimuToolKit.egg-info/PKG-INFO
AISimuToolKit.egg-info/SOURCES.txt
AISimuToolKit.egg-info/dependency_links.txt
AISimuToolKit.egg-info/requires.txt
AISimuToolKit.egg-info/top_level.txt
AISimuToolKit/exp/__init__.py
AISimuToolKit/exp/experiment.py
AISimuToolKit/exp/actions/__init__.py
AISimuToolKit/exp/actions/base_action.py
AISimuToolKit/exp/actions/finetune_action.py
AISimuToolKit/exp/actions/instruct_action.py
AISimuToolKit/exp/actions/probe_action.py
AISimuToolKit/exp/actions/reflect_action.py
AISimuToolKit/exp/actions/register.py
AISimuToolKit/exp/agents/__init__.py
AISimuToolKit/exp/agents/agent.py
AISimuToolKit/exp/agents/memory.py
AISimuToolKit/exp/toolkit/TimeStep.py
AISimuToolKit/exp/toolkit/__init__.py
AISimuToolKit/exp/toolkit/register.py
AISimuToolKit/exp/toolkit/toolkit.py
AISimuToolKit/model/__init__.py
AISimuToolKit/model/embedding.py
AISimuToolKit/model/model.py
AISimuToolKit/model/register.py
AISimuToolKit/store/__init__.py
AISimuToolKit/store/logger.py
AISimuToolKit/utils/__init__.py
AISimuToolKit/utils/utils.py
test/__init__.py
test/test_experiment.py
test/exp/__init__.py
test/exp/agents/__init__.py
test/exp/agents/test_agent.py