Metadata-Version: 2.1
Name: AISimuToolKit
Version: 0.1.3
Summary: ICIP's private utils.
Home-page: http://git.cipsup.cn/aisimulationplatform/toolkit/aisimulation
Author: Ren & Guo
Author-email: renmengjie22@mails.ucas.ac.cn,guoshiguang22@mails.ucas.edu.cn
License: MIT Licence
Keywords: pip,AISimuToolKit
Platform: any
Requires-Python: >=3.10
